XD_tool-0.2.0.dist-info/DESCRIPTION.rst
XD_tool-0.2.0.dist-info/METADATA
XD_tool-0.2.0.dist-info/RECORD
XD_tool-0.2.0.dist-info/WHEEL
XD_tool-0.2.0.dist-info/entry_points.txt
XD_tool-0.2.0.dist-info/metadata.json
XD_tool-0.2.0.dist-info/top_level.txt
xd/__init__.py
xd/tool/__init__.py
xd/tool/commands.py
xd/tool/layer.py
xd/tool/log.py
xd/tool/main.py
xd/tool/manifest.py
xd/tool/os.py
xd/tool/shell.py
xd/tool/cmd/__init__.py
xd/tool/cmd/init.py
xd/tool/cmd/layer.py
